setup.py
gadapter/__init__.py
gadapter.egg-info/PKG-INFO
gadapter.egg-info/SOURCES.txt
gadapter.egg-info/dependency_links.txt
gadapter.egg-info/requires.txt
gadapter.egg-info/top_level.txt
test/__init__.py