Metadata-Version: 1.1
Name: gadapter
Version: 0.0.1
Summary: Adapter for Gcloud - python
Home-page: https://github.com/RevelutionWind/gadapter.git
Author: plasmashadow
Author-email: plasmashadowx@gmail.com
License: Apache 2.0
Platform: UNKNOWN
Classifier: Programming Language :: Python
Classifier: Programming Language :: Python :: 2
Classifier: License :: OSI Approved :: GNU General Public License (GPL)
Classifier: Operating System :: OS Independent
Classifier: Development Status :: 1 - Planning
Classifier: Environment :: Console
